treco/__init__.py
treco/__main__.py
treco/cli.py
treco/console.py
treco/logging.py
treco/connection/__init__.py
treco/connection/base.py
treco/connection/lazy.py
treco/connection/multiplexed.py
treco/connection/pooled.py
treco/connection/preconnect.py
treco/http/__init__.py
treco/http/adapter.py
treco/http/client.py
treco/http/parser.py
treco/http/extractor/__init__.py
treco/http/extractor/base.py
treco/http/extractor/boundary.py
treco/http/extractor/cookie.py
treco/http/extractor/header.py
treco/http/extractor/jpath.py
treco/http/extractor/jwt.py
treco/http/extractor/regex.py
treco/http/extractor/xpath.py
treco/input/__init__.py
treco/input/config.py
treco/input/distributor.py
treco/metrics/__init__.py
treco/metrics/counter.py
treco/metrics/registry.py
treco/metrics/reporter.py
treco/metrics/timer.py
treco/models/__init__.py
treco/models/config.py
treco/models/context.py
treco/models/response.py
treco/orchestrator/__init__.py
treco/orchestrator/coordinator.py
treco/orchestrator/parallel_executor.py
treco/orchestrator/race_executor.py
treco/orchestrator/result_analyzer.py
treco/parser/__init__.py
treco/parser/schema_validator.py
treco/parser/validator.py
treco/parser/loaders/yaml.py
treco/parser/schema/__init__.py
treco/parser/schema/treco-config.schema.json
treco/state/__init__.py
treco/state/conditions.py
treco/state/executor.py
treco/state/machine.py
treco/sync/__init__.py
treco/sync/barrier.py
treco/sync/base.py
treco/sync/countdown_latch.py
treco/sync/semaphore.py
treco/template/__init__.py
treco/template/engine.py
treco/template/filters/__init__.py
treco/template/filters/argv.py
treco/template/filters/average.py
treco/template/filters/env.py
treco/template/filters/md5.py
treco/template/filters/sha1.py
treco/template/filters/sha256.py
treco/template/filters/totp.py
treco/wordlists/passwords-top-100.txt
treco/wordlists/passwords-top-30.txt
treco/wordlists/user-agents-1k.txt
treco/wordlists/usernames-common.txt
treco_framework-1.11.1.dist-info/METADATA
treco_framework-1.11.1.dist-info/WHEEL
treco_framework-1.11.1.dist-info/entry_points.txt
treco_framework-1.11.1.dist-info/licenses/LICENSE
treco_framework-1.11.1.dist-info/RECORD
