Metadata-Version: 2.4
Name: treco-framework
Version: 1.11.1
Summary: Tactical Race Exploitation & Concurrency Orchestrator
Project-URL: Homepage, https://github.com/maycon/treco
Project-URL: Repository, https://github.com/maycon/treco.git
Project-URL: Issues, https://github.com/maycon/treco/issues
Author-email: Maycon Vitali <maycon@hacknroll.com>
License: MIT
License-File: LICENSE
Keywords: concurrency,http,pentesting,race-condition,security,testing
Classifier: Development Status :: 4 - Beta
Classifier: Environment :: Console
Classifier: Intended Audience :: Developers
Classifier: Intended Audience :: Information Technology
Classifier: License :: OSI Approved :: MIT License
Classifier: Operating System :: OS Independent
Classifier: Programming Language :: Python :: 3
Classifier: Programming Language :: Python :: 3.10
Classifier: Programming Language :: Python :: 3.11
Classifier: Programming Language :: Python :: 3.12
Classifier: Programming Language :: Python :: 3.13
Classifier: Topic :: Security
Requires-Python: >=3.10
Requires-Dist: click>=8.3.1
Requires-Dist: colorama>=0.4.6
Requires-Dist: httpx[http2,socks]>=0.27.0
Requires-Dist: jinja2>=3.1.2
Requires-Dist: jsonpath-ng>=1.6.0
Requires-Dist: jsonschema>=4.0.0
Requires-Dist: lxml>=5.0.0
Requires-Dist: pyjwt>=2.8.0
Requires-Dist: pyotp>=2.9.0
Requires-Dist: pyyaml>=6.0.1
Provides-Extra: dev
Requires-Dist: black>=24.0.0; extra == 'dev'
Requires-Dist: pytest-cov>=4.0.0; extra == 'dev'
Requires-Dist: pytest>=8.0.0; extra == 'dev'
Requires-Dist: ruff>=0.1.0; extra == 'dev'
